genetica/__init__.py
genetica/dna.py
genetica/example.py
genetica/model.py
genetica-0.5.1.dist-info/LICENSE
genetica-0.5.1.dist-info/METADATA
genetica-0.5.1.dist-info/WHEEL
genetica-0.5.1.dist-info/top_level.txt
genetica-0.5.1.dist-info/RECORD
