Metadata-Version: 2.1
Name: genetica
Version: 0.5.1
Summary: This library allows you to take any class with certain business logic, modify it a    little and then give it back to Genetica to optimize.
Home-page: https://github.com/VASemenov/genetica
Author: Vladimir Semenov
Author-email: subatiq@gmail.com
License: MIT
Download-URL: https://github.com/VASemenov/genetica/archive/0.1.tar.gz
Keywords: genetic,optimization,minimalistic
Platform: UNKNOWN
Classifier: Development Status :: 3 - Alpha
Classifier: Intended Audience :: Developers
Classifier: Topic :: Software Development :: Build Tools
Classifier: License :: OSI Approved :: MIT License
Classifier: Programming Language :: Python :: 3
Classifier: Programming Language :: Python :: 3.4
Classifier: Programming Language :: Python :: 3.5
Classifier: Programming Language :: Python :: 3.6
Classifier: Programming Language :: Python :: 3.7
Classifier: Programming Language :: Python :: 3.8
Requires-Dist: matplotlib
